README.rst
setup.cfg
setup.py
pyrowire/__init__.py
pyrowire/pyrowire.py
pyrowire.egg-info/PKG-INFO
pyrowire.egg-info/SOURCES.txt
pyrowire.egg-info/dependency_links.txt
pyrowire.egg-info/entry_points.txt
pyrowire.egg-info/requires.txt
pyrowire.egg-info/top_level.txt
pyrowire/config/__init__.py
pyrowire/config/configuration.py
pyrowire/decorators/__init__.py
pyrowire/decorators/decorators.py
pyrowire/messaging/__init__.py
pyrowire/messaging/message.py
pyrowire/messaging/send.py
pyrowire/resources/__init__.py
pyrowire/resources/profanity.py
pyrowire/resources/settings.py
pyrowire/resources/console_scripts/__init__.py
pyrowire/resources/console_scripts/console_scripts.py
pyrowire/resources/sample/Procfile
pyrowire/resources/sample/__init__.py
pyrowire/resources/sample/app.py
pyrowire/resources/sample/requirements.txt
pyrowire/resources/sample/settings.py
pyrowire/routes/__init__.py
pyrowire/routes/queue_message.py
pyrowire/runner/__init__.py
pyrowire/runner/runner.py
pyrowire/tasks/__init__.py
pyrowire/tasks/tasks.py
pyrowire/validators/__init__.py
pyrowire/validators/validators.py
pyrowire/voice/__init__.py
test/test_app.py
test/test_settings.py