Metadata-Version: 1.1
Name: pyrowire
Version: 0.8.1
Summary: Super-fast Twilio SMS response API
Home-page: https://github.com/wieden-kennedy/pyrowire
Author: Keith Hamilton
Author-email: keith.hamilton@wk.com
License: BSD License
Keywords: api flask framework sms web messaging twilio redis
Platform: UNKNOWN
Classifier: Development Status :: 4 - Beta
Classifier: Intended Audience :: Developers
Classifier: Topic :: Software Development
Classifier: Topic :: Software Development :: Libraries :: Application Frameworks
Classifier: License :: OSI Approved :: BSD License
Classifier: Programming Language :: Python
Classifier: Programming Language :: Python :: 2.6
Classifier: Programming Language :: Python :: 2.7
